include/mmtf.hpp
include/msgpack.hpp
include/msgpack/create_object_visitor_decl.hpp
include/msgpack/null_visitor_decl.hpp
include/msgpack/fbuffer_decl.hpp
include/msgpack/fbuffer.hpp
include/msgpack/preprocessor.hpp
include/msgpack/object_fwd_decl.hpp
include/msgpack/vrefbuffer_decl.hpp
include/msgpack/object.hpp
include/msgpack/meta.hpp
include/msgpack/sbuffer_decl.hpp
include/msgpack/pack_decl.hpp
include/msgpack/iterator.hpp
include/msgpack/cpp_config.hpp
include/msgpack/unpack.hpp
include/msgpack/predef.h
include/msgpack/x3_unpack_decl.hpp
include/msgpack/versioning.hpp
include/msgpack/create_object_visitor.hpp
include/msgpack/x3_parse.hpp
include/msgpack/null_visitor.hpp
include/msgpack/parse.hpp
include/msgpack/sysdep.hpp
include/msgpack/object_decl.hpp
include/msgpack/cpp_config_decl.hpp
include/msgpack/parse_decl.hpp
include/msgpack/zone.hpp
include/msgpack/vrefbuffer.hpp
include/msgpack/parse_return.hpp
include/msgpack/zbuffer.hpp
include/msgpack/version_master.hpp
include/msgpack/unpack_define.hpp
include/msgpack/pack.hpp
include/msgpack/zone_decl.hpp
include/msgpack/type.hpp
include/msgpack/assert.hpp
include/msgpack/x3_parse_decl.hpp
include/msgpack/x3_unpack.hpp
include/msgpack/unpack_exception.hpp
include/msgpack/iterator_decl.hpp
include/msgpack/sbuffer.hpp
include/msgpack/cpp_version.hpp
include/msgpack/unpack_decl.hpp
include/msgpack/gcc_atomic.hpp
include/msgpack/zbuffer_decl.hpp
include/msgpack/meta_decl.hpp
include/msgpack/version.hpp
include/msgpack/object_fwd.hpp
include/msgpack/predef/os.h
include/msgpack/predef/platform.h
include/msgpack/predef/other.h
include/msgpack/predef/make.h
include/msgpack/predef/version.h
include/msgpack/predef/version_number.h
include/msgpack/predef/library.h
include/msgpack/predef/hardware.h
include/msgpack/predef/language.h
include/msgpack/predef/architecture.h
include/msgpack/predef/compiler.h
include/msgpack/predef/other/workaround.h
mmtf_cppy-1.1.6.dist-info/WHEEL
mmtf_cppy-1.1.6.dist-info/RECORD
mmtf_cppy-1.1.6.dist-info/entry_points.txt
mmtf_cppy-1.1.6.dist-info/METADATA
mmtf_cppy-1.1.6.dist-info/licenses/LICENSE
