Metadata-Version: 2.1
Name: mmtf_cppy
Version: 1.1.6
Summary: Toolkit for handling MMTF formatted macromolecular data
Author-Email: Danny Farrell <16297104+danpf@users.noreply.github.com>
Classifier: License :: OSI Approved :: MIT License
Classifier: Programming Language :: Python :: 3 :: Only
Classifier: Programming Language :: Python :: 3.8
Classifier: Programming Language :: Python :: 3.9
Classifier: Programming Language :: Python :: 3.10
Classifier: Programming Language :: Python :: 3.11
Classifier: Programming Language :: Python :: 3.12
Requires-Python: >=3.8
Requires-Dist: numpy
Requires-Dist: msgpack
